setup.py
Vallegameoflife/__main__.py
Vallegameoflife.egg-info/PKG-INFO
Vallegameoflife.egg-info/SOURCES.txt
Vallegameoflife.egg-info/dependency_links.txt
Vallegameoflife.egg-info/not-zip-safe
Vallegameoflife.egg-info/requires.txt
Vallegameoflife.egg-info/top_level.txt
Vallegameoflife/game/Cell.py
Vallegameoflife/game/Form.py
Vallegameoflife/game/Runner.py
Vallegameoflife/screens/GameOfLife.py
Vallegameoflife/screens/Ihm.py
Vallegameoflife/game/Cell.py
Vallegameoflife/game/Form.py
Vallegameoflife/game/Runner.py
Vallegameoflife/screens/GameOfLife.py
Vallegameoflife/screens/Ihm.py
bin/Vallegameoflife
bin/Vallegameoflife.bat